sl_abuse/__init__.py
sl_abuse/__main__.py
sl_abuse-1.4.5.dist-info/LICENSE
sl_abuse-1.4.5.dist-info/METADATA
sl_abuse-1.4.5.dist-info/WHEEL
sl_abuse-1.4.5.dist-info/entry_points.txt
sl_abuse-1.4.5.dist-info/top_level.txt
sl_abuse-1.4.5.dist-info/RECORD
