Metadata-Version: 2.1
Name: sl-abuse
Version: 1.4.5
Summary: UNKNOWN
Home-page: https://github.com/shehan9909/whatsapp
Author: shehan_slahiru
Author-email: www.shehan6472@gmail.com
License: MIT
Platform: UNKNOWN
Classifier: License :: OSI Approved :: MIT License
Classifier: Programming Language :: Python :: 3
Classifier: Programming Language :: Python :: 3.9
License-File: LICENSE
Requires-Dist: twilio
